pydantic_ai_mlx_lm/__init__.py
pydantic_ai_mlx_lm/agent_model.py
pydantic_ai_mlx_lm/model.py
pydantic_ai_mlx_lm/py.typed
pydantic_ai_mlx_lm/response.py
pydantic_ai_mlx_lm/stream.py
pydantic_ai_mlx_lm/utils.py
pydantic_ai_mlx_lm-0.1.7.dist-info/METADATA
pydantic_ai_mlx_lm-0.1.7.dist-info/WHEEL
pydantic_ai_mlx_lm-0.1.7.dist-info/RECORD
