Metadata-Version: 2.4
Name: pydantic-ai-mlx-lm
Version: 0.1.7
Summary: Run MLX compatible HuggingFace models with Pydantic AI
Author-email: Doruk Gezici <doruk@gezici.me>
Requires-Python: >=3.12
Requires-Dist: mlx-lm>=0.21.1
Requires-Dist: openai>=1.59.9
Requires-Dist: pydantic-ai-slim>=0.0.19
